plur/__init__.py
plur/py.typed
plur-1.0.0.dist-info/METADATA
plur-1.0.0.dist-info/WHEEL
plur-1.0.0.dist-info/RECORD
